moddotplot/__init__.py
moddotplot/__main__.py
moddotplot/const.py
moddotplot/estimate_identity.py
moddotplot/interactive.py
moddotplot/moddotplot.py
moddotplot/parse_fasta.py
moddotplot/static_plots.py
moddotplot-0.9.8.dist-info/licenses/LICENSE
moddotplot-0.9.8.dist-info/METADATA
moddotplot-0.9.8.dist-info/WHEEL
moddotplot-0.9.8.dist-info/entry_points.txt
moddotplot-0.9.8.dist-info/top_level.txt
moddotplot-0.9.8.dist-info/RECORD
