Metadata-Version: 2.4
Name: ModDotPlot
Version: 0.9.8
Author: Michael Schatz, Adam Phillippy
Author-email: Alex Sweeten <alex.sweeten@nih.gov>
Maintainer-email: Alex Sweeten <alex.sweeten@nih.gov>
License: MIT License
Keywords: dotplot,sketching,modimizer,heatmap
Requires-Python: >=3.7
License-File: LICENSE
Requires-Dist: pysam
Requires-Dist: pandas
Requires-Dist: plotly
Requires-Dist: dash
Requires-Dist: plotnine==0.12.4
Requires-Dist: palettable
Requires-Dist: mmh3
Requires-Dist: setproctitle
Requires-Dist: numpy
Requires-Dist: pillow
Requires-Dist: patchworklib==0.6.3
Requires-Dist: cairosvg
Requires-Dist: pygenometracks
Requires-Dist: svgutils
Requires-Dist: cooler
Provides-Extra: test
Requires-Dist: pytest; extra == "test"
Requires-Dist: pytest-cov; extra == "test"
Dynamic: license-file
